{"adult":false,"also_known_as":[],"biography":"From Wikipedia, the free encyclopedia.\n\nBrenna O'Brien (born March 9, 1991) is a Canadian actress. She is best known for voicing Rin in the anime series Inuyasha.\n\nDescription above from the Wikipedia article Brenna O'Brien, licensed under CC-BY-SA, full list of contributors on Wikipedia.","birthday":"1991-03-09","deathday":null,"gender":1,"homepage":null,"id":87736,"imdb_id":"nm1378650","known_for_department":"Acting","name":"Brenna O'Brien","place_of_birth":"Canada","popularity":6.563,"profile_path":"/uELRo1iat97rVeyBxCrpqy6v1OR.jpg"}
