{"adult":false,"also_known_as":[],"biography":"From Wikipedia, the free encyclopedia.\n\nAdam Carolla (born May 27, 1964) is an American radio personality, television host, comedian, and actor. He currently hosts The Adam Carolla Show, a talk show distributed as a podcast on the ACE Broadcasting Network.\n\nCarolla is also known as being the co-host of the radio show Loveline from 1995 to 2005 (and its television incarnation on MTV from 1996 to 2000), as the co-host of the television program The Man Show (1999–2004), and as the co-creator and performer on the television program Crank Yankers (2002–2007).\n\nIn November 2010 Carolla's book In Fifty Years We'll All Be Chicks debuted on the New York Times Best Seller List for hardcover non-fiction.\n\nDescription above from the Wikipedia article Adam Carolla, licensed under CC-BY-SA, full list of contributors on Wikipedia.","birthday":"1964-05-27","deathday":null,"gender":2,"homepage":null,"id":76245,"imdb_id":"nm0004805","known_for_department":"Acting","name":"Adam Carolla","place_of_birth":"Los Angeles, California, USA","popularity":4.64,"profile_path":"/47k9w6HRLnGeU0gVtMeTPJs3ief.jpg"}
