{"adult":false,"also_known_as":[],"biography":"From Wikipedia, the free encyclopedia.\n\nDoris May Roberts (November 4, 1925 – April 17, 2016) was an American actress of film, stage and television. She has received five Emmy Awards. With a seven-decade career, she is most widely known for playing Marie Barone on Everybody Loves Raymond from 1996–2005.\n\nDescription above from the Wikipedia article Doris Roberts, licensed under CC-BY-SA, full list of contributors on Wikipedia.​","birthday":"1925-11-04","deathday":"2016-04-17","gender":1,"homepage":null,"id":45863,"imdb_id":"nm0005368","known_for_department":"Acting","name":"Doris Roberts","place_of_birth":"St. Louis, Missouri, U.S.","popularity":7.278,"profile_path":"/bfJjsAKKRqUhm1lh2QC8u2atrov.jpg"}
