{"adult":false,"also_known_as":[],"biography":"Diane Kurys is a French director, producer, filmmaker and actress. She was born in Lyon, Rhône, France, the younger of two daughters. Several of her films as director are semi-autobiographical.","birthday":"1948-12-03","deathday":null,"gender":1,"homepage":null,"id":77005,"imdb_id":"nm0476123","known_for_department":"Directing","name":"Diane Kurys","place_of_birth":"Lyon, France","popularity":1.646,"profile_path":"/34hMzzECWUmK5i8W1ku1I84r13x.jpg"}
