{"adult":false,"also_known_as":["Sean McCaan "],"biography":"From Wikipedia, the free encyclopedia.\n\nSean McCann (born September 24, 1935) is one of Canada's most successful character actors and has been in the business for over 40 years. Winner of the prestigious Earle Grey Award for his lifetime achievement in television, Sean McCann has appeared in over 150 movies, television shows and plays.\n\nDescription above from the Wikipedia article Sean McCann (actor), licensed under CC-BY-SA, full list of contributors on Wikipedia","birthday":"1935-09-24","deathday":"2019-06-13","gender":2,"homepage":null,"id":17646,"imdb_id":"nm0564921","known_for_department":"Acting","name":"Sean McCann","place_of_birth":"Windsor, Ontario, Canada","popularity":1.716,"profile_path":"/sVT3HB2rIkfgZ87mCiGmYS2OrzF.jpg"}
