{"adult":false,"also_known_as":["末岡一郎"],"biography":"Born in Sapporo, in 1965. Studied at Tokyo Science University in chemistry dept. Began making film works since 1985. Many of the 90 films were produced on Super-8 and 16mm film.\n\nNow living as a film maker in Tokyo and co-founder of the \"Film-Makers' Information Center (FMIC)\" experimental film/video group, which has curated and presented the several screening events of the independent film-maker's works in Japan since 2002 to 2006.\n\nCurrently teaching film-making at Asagaya College of Art & Design and also teaching hand-developing workshops at other art school or art gallery.","birthday":null,"deathday":null,"gender":2,"homepage":null,"id":1760413,"imdb_id":null,"known_for_department":"Directing","name":"Ichiro Sueoka","place_of_birth":"Sapporo, Japan","popularity":0.6,"profile_path":null}
