{"adult":false,"also_known_as":["Joosua Huurteinen"],"biography":"Heikki Kinnunen (born 8 April 1946, in Raahe) is a Finnish actor, who became well known in the beginning of the 1970s in the comedy program Ällitälli. Kinnunen was known specially for his roles in comedy films and -series. He has played the leading role in Vääpeli Körmy films and appeared in five Uuno Turhapuro films.\n\nKinnunen's most famous comedic catch-phrase is \"Onks Viljoo näkyny?\" (\"You seen Viljo?\") born from a skit in which he shows up asking people this question then inquiring something about what they are currently doing. Who Viljo is or why Kinnunen's character is looking for him is never explained in the skits themselves.\n\nSource: Article \"Heikki Kinnunen\" from Wikipedia in english, licensed under CC-BY-SA 3.0.","birthday":"1946-04-08","deathday":null,"gender":2,"homepage":null,"id":147771,"imdb_id":"nm0455797","known_for_department":"Acting","name":"Heikki Kinnunen","place_of_birth":"Raahe, Finland","popularity":1.399,"profile_path":"/9KI8t1EHfcIFqobQ07GtkoOrRay.jpg"}
