{"adult":false,"also_known_as":["Jane Moira Cusack","Sinead Cusack"],"biography":"​From Wikipedia, the free encyclopedia.  \n\nSinéad Moira Cusack (born 18 February 1948) is an Irish stage, television and film actress. She has received two Tony Award nominations: once for Best Leading Actress in Much Ado About Nothing (1985), and again for Best Featured Actress in Rock 'n' Roll (2008).\n\nDescription above from the Wikipedia article Sinéad Cusack, licensed under CC-BY-SA, full list of contributors on Wikipedia.","birthday":"1948-02-18","deathday":null,"gender":1,"homepage":null,"id":11281,"imdb_id":"nm0193661","known_for_department":"Acting","name":"Sinéad Cusack","place_of_birth":"Dalkey, County Dublin, Ireland","popularity":15.113,"profile_path":"/3WTdtZqMu3dA7YLSLWtAbRcmCuo.jpg"}
