{"adult":false,"also_known_as":[],"biography":"​From Wikipedia, the free encyclopedia\n\nJason Jones (born June 3, 1967) is a Canadian actor and comedian who is a correspondent on The Daily Show with Jon Stewart.\n\nDescription above from the Wikipedia article Jason Jones (actor), licensed under CC-BY-SA, full list of contributors on Wikipedia.","birthday":"1967-06-03","deathday":null,"gender":2,"homepage":null,"id":185805,"imdb_id":"nm0428319","known_for_department":"Acting","name":"Jason Jones","place_of_birth":"Hamilton, Ontario, Canada","popularity":5.025,"profile_path":"/gvvCYf3zBlJhJbVv2l0Ya2eRk5W.jpg"}
