{"adult":false,"also_known_as":["Καλίστα Φλόκχαρτ","Καλίστα Κέι Φλόκχαρτ"],"biography":"Calista Flockhart (born November 11, 1964) is an American actress who is primarily recognized for her work in television. She is best known for playing the title character in Ally McBeal, and her role as Cat Grant in Supergirl.\n\nDuring her career, she has received a Golden Globe Award, a Screen Actors Guild Award and three Emmy Award nominations.","birthday":"1964-11-11","deathday":null,"gender":1,"homepage":null,"id":49148,"imdb_id":"nm0001222","known_for_department":"Acting","name":"Calista Flockhart","place_of_birth":"Freeport, Illinois, USA","popularity":16.872,"profile_path":"/s0YPPAaIO5fnWI9baxp4TIkUXmn.jpg"}
