{"adult":false,"also_known_as":["Biao Yuen","Bill Yuen","元彪 ","Hsia Ling-Jun","Jimmy Yuen","원표"],"biography":"Yuen Biao (Chinese: 元彪, born 26 July 1957) is a Hong Kong actor and martial artist. He specialises in acrobatics and Chinese martial arts and has worked on over 80 films as actor, stuntman and action choreographer. Along with Peking Opera School \"brothers\" at the China Drama Academy, Sammo Hung and Jackie Chan, he was  a member of the\"Seven Little Fortunes\" performance troupe in Yu Jim-Yuen's China Drama Academy's Peking Opera School. Was a member of the Sammo Hung Stuntmen's Association.","birthday":"1957-07-26","deathday":null,"gender":2,"homepage":null,"id":62414,"imdb_id":"nm0950707","known_for_department":"Acting","name":"Yuen Biao","place_of_birth":"Hong Kong, China","popularity":10.927,"profile_path":"/pgO9Im1QKPjLozvsWODLtZDTjw7.jpg"}
