{"adult":false,"also_known_as":["Joe Sikora","Joseph Sikkora"],"biography":"Sikora was born in Chicago, Illinois, to mother Barbara and father Albin, one of three boys, and lived in the Jefferson Park and Norwood Park neighborhoods. He is of Polish and Dutch descent. Sikora graduated from Notre Dame College Prep in 1994. He studied acting at Columbia College Chicago, where he earned his MA in theater.","birthday":"1976-06-27","deathday":null,"gender":2,"homepage":null,"id":82631,"imdb_id":"nm0797746","known_for_department":"Acting","name":"Joseph Sikora","place_of_birth":"Chicago, Illinois, USA ","popularity":14.143,"profile_path":"/xql9QZqU9povZhRIkuXym2FtoFq.jpg"}
