{"adult":false,"also_known_as":[],"biography":"From Wikipedia\n\nIda Di Benedetto (born 3 June 1945) is an Italian actress and film producer.\n\nShe appeared in 53 films and television shows between 1974 and 2004. She starred in the film The Whores, which was entered into the 1994 Cannes Film Festival. She won the Nastro d'Argento (Silver Ribbon) for Best Supporting Actress in 1981 for her supporting role as Maria Rosa in Fontamara and the following year she won the Nastro d'Argento for Best Actress for Immacolata e Concetta.","birthday":"1945-06-03","deathday":null,"gender":1,"homepage":null,"id":45196,"imdb_id":"nm0223652","known_for_department":"Acting","name":"Ida Di Benedetto","place_of_birth":"Naples, Italy","popularity":1.4,"profile_path":"/9uIMhLseXL2VIdVme9S9TNk83CL.jpg"}
