{"adult":false,"also_known_as":["  Patrick Williams "],"biography":"From Wikipedia, the free encyclopedia. Pat Williams (sometimes credited as Patrick Williams) is a Canadian television director and producer.\n\nWorking since the 1980s as a camera operator on such films as Police Academy (1984) and Cool Runnings (1993). Making his directorial debut in 1997, directing an episodes of The Secret World of Alex Mack. Some of his other television credits include So Weird, Strange Days at Blake Holsey High, Kyle XY, Smallville, Instant Star, Degrassi: The Next Generation, Kevin Hill, Aaron Stone, The Troop and Shattered.","birthday":null,"deathday":null,"gender":2,"homepage":null,"id":106964,"imdb_id":"nm0931426","known_for_department":"Directing","name":"Pat Williams","place_of_birth":null,"popularity":1.947,"profile_path":null}
