{"adult":false,"also_known_as":["Timothy Daly"],"biography":"​From Wikipedia, the free encyclopedia.\n\nJames Timothy Daly (born March 1, 1956) is an American actor and producer. He is known for his role as Joe Hackett on the NBC sitcom Wings and his voice role as Clark Kent/Superman in Superman: The Animated Series, as well as his recurring role as the drug-addicted screenwriter J.T. Dolan on The Sopranos (for which he was nominated for an Emmy Award). He starred as Pete Wilder on Private Practice from 2007 to 2012. Since 2014, he has portrayed Henry McCord, husband of the titular character, on the CBS drama Madam Secretary.\n\nDescription above from the Wikipedia article Tim Daly, licensed under CC-BY-SA, full list of contributors on Wikipedia","birthday":"1956-03-01","deathday":null,"gender":2,"homepage":null,"id":68122,"imdb_id":"nm0004857","known_for_department":"Acting","name":"Tim Daly","place_of_birth":"New York City, New York, USA","popularity":11.509,"profile_path":"/sFTV1k3gJK49JVZsEFkH1EZCVg1.jpg"}
