{"adult":false,"also_known_as":[],"biography":"Susan Prior is an Australian actress. She won the 2014 AACTA Award for Best Actress in a Supporting Role for her role in The Rover and was nominated for the 2012 AACTA Award for Best Guest or Supporting Actress in a Television Drama for Puberty Blues. She was twice nominated for the Helpmann Award for Best Female Actor in a Supporting Role in a Play, in 2008 for Riflemind and in 2014 for Small and Tired.","birthday":null,"deathday":null,"gender":1,"homepage":null,"id":76069,"imdb_id":"nm0697960","known_for_department":"Acting","name":"Susan Prior","place_of_birth":null,"popularity":2.492,"profile_path":"/6WSWZWUzFJXFBlzzCvnJJrh8Jws.jpg"}
