{"adult":false,"also_known_as":[],"biography":"Karina Arroyave (born July 16, 1969) is a Colombian television and film actress, likely best known as Jamey Farrell in 24.\n\nShe has appeared in a total of 3 \"dedicated teacher\" films where the teacher tries to get the inner city students to want to learn (One Eight Seven, Dangerous Minds and Lean on Me). She also had a role in Crash as wife of Daniel, the Latino locksmith.\n\nDescription above from the Wikipedia article Karina Arroyave, licensed under CC-BY-SA, full list of contributors on Wikipedia.","birthday":"1969-07-16","deathday":null,"gender":1,"homepage":null,"id":18282,"imdb_id":"nm0037410","known_for_department":"Acting","name":"Karina Arroyave","place_of_birth":"Colombia","popularity":6.877,"profile_path":"/dsMtfSCLeL6xAQF1XHNH3QF0E97.jpg"}
