{"adult":false,"also_known_as":[],"biography":"Tiago Guedes was born on June 20, 1971 in Porto, Portugal as Tiago Guedes de Carvalho. He is a director and writer, known for A Herdade (2019), Coisa Ruim (2006) and Coro dos Amantes (2014). He has been married to Isabel Abreu since January 1, 2001. They have two children, Tiago and Maria. He's the younger brother of Rodrigo Guedes de Carvalho and he's son of Rodrigo Jorge Ferreira Guedes de Carvalho and wife. His father is a first cousin of Paula Guedes.","birthday":"1971-06-20","deathday":null,"gender":2,"homepage":null,"id":116601,"imdb_id":"nm0345743","known_for_department":"Directing","name":"Tiago Guedes","place_of_birth":"Porto, Portugal","popularity":0.6,"profile_path":null}
