{"adult":false,"also_known_as":["Кевин МакКидд"],"biography":"Kevin McKidd (born 9 August 1973) is a Scottish television and film actor and director. He is known for his prominent television roles, including his performances as Lucius Vorenus in Rome, as Poseidon in Percy Jackson & the Olympians: The Lightning Thief, and as Dr. Owen Hunt in Grey's Anatomy.\n\nHe has also appeared in films such as Trainspotting, Bedrooms and Hallways, Kingdom of Heaven, The Last Legion, Hannibal Rising, The Acid House, Made of Honor and had the lead role in the cult-classic British horror film Dog Soldiers.\n\nMcKidd has done voice work and voiced the character of Jezz Torrent, flame haired lead singer of the fictional Scottish hard rock band Love Fist in the video games \"Grand Theft Auto: Vice City\". He also voiced Captain \"Soap\" MacTavish in Call of Duty: Modern Warfare 2.\n\nDescription above from the Wikipedia article Kevin McKidd, licensed under CC-BY-SA, full list of contributors on Wikipedia.","birthday":"1973-08-09","deathday":null,"gender":2,"homepage":null,"id":9013,"imdb_id":"nm0571727","known_for_department":"Acting","name":"Kevin McKidd","place_of_birth":"Elgin, Moray, Scotland, UK","popularity":11.377,"profile_path":"/KtmEKOSehmQ35JfGjEjpqlypbP.jpg"}
