{"adult":false,"also_known_as":["멜리사 맥카시"],"biography":"Melissa McCarthy (born August 26, 1970) is an American actress known most for her portrayal of chef Sookie St. James, Lorelai Gilmore's best friend, on the television series Gilmore Girls, and currently as the title character Molly Flynn on the CBS sitcom Mike &amp; Molly.\n\nDescription above from the Wikipedia article Melissa McCarthy, licensed under CC-BY-SA, full list of contributors on Wikipedia.","birthday":"1970-08-26","deathday":null,"gender":1,"homepage":null,"id":55536,"imdb_id":"nm0565250","known_for_department":"Acting","name":"Melissa McCarthy","place_of_birth":"Plainfield, Illinois, USA","popularity":18.63,"profile_path":"/nRNMJlqR33j84cGdB0RxstV3NYm.jpg"}
