{"adult":false,"also_known_as":["维罗尼卡·费瑞尔"],"biography":"Veronica Maria Cäcilia Ferres (born 10 June 1965) is a German actress who gained fame as Pierre Richard's co-star in the French TV-movie Sans famille and as the horrible Mme. Thénardier in the 2000 French TV miniseries Les Misérables. She also starred in the Oscar-nominated German movie Schtonk (1992).\n\nIn 2007 she played with Willem Dafoe and Jeff Goldblum in the international cinema production Adam Resurrected directed by Paul Schrader.\n\nDescription above from the Wikipedia article Veronica Ferres, licensed under CC-BY-SA, full list of contributors on Wikipedia.​","birthday":"1965-06-10","deathday":null,"gender":1,"homepage":"https://www.veronicaferres.com/","id":23524,"imdb_id":"nm0274704","known_for_department":"Acting","name":"Veronica Ferres","place_of_birth":"Solingen, Germany","popularity":6.783,"profile_path":"/coHFoFuANZyDaIUBuJoOeSgGEKl.jpg"}
