{"adult":false,"also_known_as":["Margaret Moran Cho","조모란","마거릿 조"],"biography":"Margaret Cho (born December 5, 1968) is an American comedian, fashion designer, actress, author, and recording artist. Cho is best known for her stand-up routines, through which she critiques social and political problems, especially those pertaining to race and sexuality. She has also directed and appeared in music videos and has her own clothing line. She has frequently supported LGBT rights and has won awards for her humanitarian efforts on behalf of women, the transgender community, Asians, and the LGBT community. As an actress she has played more serious parts, such as that of John Travolta's long-suffering FBI colleague in the action movie Face/Off. She is part of the hit TV series Drop Dead Diva on Lifetime Television, playing the role of Teri Lee, a paralegal assistant.\n\n​From Wikipedia, the free encyclopedia","birthday":"1968-12-05","deathday":null,"gender":1,"homepage":null,"id":11152,"imdb_id":"nm0158632","known_for_department":"Acting","name":"Margaret Cho","place_of_birth":"San Francisco, California, USA","popularity":6.055,"profile_path":"/lsHpa4aRrBMn7LtFX8AdPTFBMGY.jpg"}
