{"adult":false,"also_known_as":["David Russell Strathairn","Дэвид Стрэтэйрн"],"biography":"An American film and television actor, best known for his portrayal of journalist Edward R. Murrow in the feature film \"Good Night, and Good Luck\", for which he was nominated for an Academy Award.","birthday":"1949-01-26","deathday":null,"gender":2,"homepage":null,"id":11064,"imdb_id":"nm0000657","known_for_department":"Acting","name":"David Strathairn","place_of_birth":"San Francisco, California, USA","popularity":13.34,"profile_path":"/fhkvTcrCDPTAclTnE7sqQS1NZKq.jpg"}
