{"adult":false,"also_known_as":[],"biography":"Kelly Rowan (born October 26, 1965) is a Canadian television and film actress and former fashion model. She is best known for portraying Kirsten Cohen on The O.C.\n\nFrom Wikipedia, the free encyclopedia.","birthday":"1965-10-26","deathday":null,"gender":1,"homepage":null,"id":47757,"imdb_id":"nm0746414","known_for_department":"Acting","name":"Kelly Rowan","place_of_birth":"Ottawa - Ontario - Canada","popularity":17.486,"profile_path":"/xPBHrefHV3yqtvdo9nUlPG7jCO9.jpg"}
