{"adult":false,"also_known_as":["Raymond Lee"],"biography":"Moira Lang (previously credited as Raymond Lee) is a Filipino filmmaker and writer. Producing socially relevant works with many involving LGBT issues, Lang is prominently known for their work on the films 'Norte, Hangganan ng Kasaysayan,' Ang Pagdadalaga ni Maximo Oliveros, and Zombadings.","birthday":null,"deathday":null,"gender":3,"homepage":null,"id":1040545,"imdb_id":"nm0498066","known_for_department":"Writing","name":"Moira Lang","place_of_birth":null,"popularity":4.128,"profile_path":"/2CdnWOtWMZ9vAXr52qUqiik6Fhj.jpg"}
